LICENSE
README.md
setup.cfg
setup.py
LiBai.egg-info/PKG-INFO
LiBai.egg-info/SOURCES.txt
LiBai.egg-info/dependency_links.txt
LiBai.egg-info/requires.txt
LiBai.egg-info/top_level.txt
libai/__init__.py
libai/version.py
libai/config/__init__.py
libai/config/arguments.py
libai/config/config.py
libai/config/instantiate.py
libai/config/lazy.py
libai/config/configs/bert_large_pretrain.py
libai/config/configs/gpt2_pretrain.py
libai/config/configs/swin_cifar100.py
libai/config/configs/swin_imagenet.py
libai/config/configs/t5_large_pretrain.py
libai/config/configs/t5_pp_pretrain.py
libai/config/configs/vit_imagenet.py
libai/config/configs/common/optim.py
libai/config/configs/common/tokenizer.py
libai/config/configs/common/train.py
libai/config/configs/common/data/bert_dataset.py
libai/config/configs/common/data/cifar100.py
libai/config/configs/common/data/gpt_dataset.py
libai/config/configs/common/data/imagenet.py
libai/config/configs/common/data/t5_dataset.py
libai/config/configs/common/models/bert.py
libai/config/configs/common/models/gpt.py
libai/config/configs/common/models/graph.py
libai/config/configs/common/models/t5.py
libai/config/configs/common/models/swin/swin_base_patch4_window12_384.py
libai/config/configs/common/models/swin/swin_base_patch4_window7_224.py
libai/config/configs/common/models/swin/swin_large_patch4_window12_384.py
libai/config/configs/common/models/swin/swin_large_patch4_window7_224.py
libai/config/configs/common/models/swin/swin_small_patch4_window7_224.py
libai/config/configs/common/models/swin/swin_tiny_c24_patch4_window8_256.py
libai/config/configs/common/models/swin/swin_tiny_patch4_window7_224.py
libai/config/configs/common/models/vit/vit_base_patch16_224.py
libai/config/configs/common/models/vit/vit_base_patch32_224.py
libai/config/configs/common/models/vit/vit_giant_patch14_224.py
libai/config/configs/common/models/vit/vit_gigantic_patch14_224.py
libai/config/configs/common/models/vit/vit_huge_patch14_224.py
libai/config/configs/common/models/vit/vit_large_patch16_224.py
libai/config/configs/common/models/vit/vit_large_patch32_224.py
