Metadata-Version: 1.0
Name: LiBai
Version: 0.0.1.4
Summary: Toolkit for Pretraining Models with OneFlow
Home-page: UNKNOWN
Author: UNKNOWN
Author-email: UNKNOWN
License:                                  Apache License
